sentry_sdk/__init__.py
sentry_sdk/_compat.py
sentry_sdk/_functools.py
sentry_sdk/_lru_cache.py
sentry_sdk/_queue.py
sentry_sdk/_types.py
sentry_sdk/_werkzeug.py
sentry_sdk/api.py
sentry_sdk/attachments.py
sentry_sdk/client.py
sentry_sdk/consts.py
sentry_sdk/debug.py
sentry_sdk/envelope.py
sentry_sdk/hub.py
sentry_sdk/metrics.py
sentry_sdk/monitor.py
sentry_sdk/profiler.py
sentry_sdk/py.typed
sentry_sdk/scope.py
sentry_sdk/scrubber.py
sentry_sdk/serializer.py
sentry_sdk/session.py
sentry_sdk/sessions.py
sentry_sdk/spotlight.py
sentry_sdk/tracing.py
sentry_sdk/tracing_utils.py
sentry_sdk/tracing_utils_py2.py
sentry_sdk/tracing_utils_py3.py
sentry_sdk/transport.py
sentry_sdk/utils.py
sentry_sdk/worker.py
sentry_sdk/crons/__init__.py
sentry_sdk/crons/api.py
sentry_sdk/crons/consts.py
sentry_sdk/crons/decorator.py
sentry_sdk/db/__init__.py
sentry_sdk/db/explain_plan/__init__.py
sentry_sdk/db/explain_plan/django.py
sentry_sdk/db/explain_plan/sqlalchemy.py
sentry_sdk/integrations/__init__.py
sentry_sdk/integrations/_asgi_common.py
sentry_sdk/integrations/_wsgi_common.py
sentry_sdk/integrations/aiohttp.py
sentry_sdk/integrations/argv.py
sentry_sdk/integrations/ariadne.py
sentry_sdk/integrations/arq.py
sentry_sdk/integrations/asgi.py
sentry_sdk/integrations/asyncio.py
sentry_sdk/integrations/asyncpg.py
sentry_sdk/integrations/atexit.py
sentry_sdk/integrations/aws_lambda.py
sentry_sdk/integrations/beam.py
sentry_sdk/integrations/boto3.py
sentry_sdk/integrations/bottle.py
sentry_sdk/integrations/celery.py
sentry_sdk/integrations/chalice.py
sentry_sdk/integrations/clickhouse_driver.py
sentry_sdk/integrations/cloud_resource_context.py
sentry_sdk/integrations/dedupe.py
sentry_sdk/integrations/excepthook.py
sentry_sdk/integrations/executing.py
sentry_sdk/integrations/falcon.py
sentry_sdk/integrations/fastapi.py
sentry_sdk/integrations/flask.py
sentry_sdk/integrations/gcp.py
sentry_sdk/integrations/gnu_backtrace.py
sentry_sdk/integrations/gql.py
sentry_sdk/integrations/graphene.py
sentry_sdk_pubsub-1.39.1.1.dist-info/LICENSE
sentry_sdk_pubsub-1.39.1.1.dist-info/METADATA
sentry_sdk_pubsub-1.39.1.1.dist-info/WHEEL
sentry_sdk_pubsub-1.39.1.1.dist-info/top_level.txt
sentry_sdk_pubsub-1.39.1.1.dist-info/RECORD
