Metadata-Version: 2.1
Name: sentry-sdk-pubsub
Version: 1.39.1.1
Summary: Python client for Sentry (https://sentry.io) with PubSub support
Home-page: https://github.com/getsentry/sentry-python
Author: Sentry Team and Contributors
Author-email: hello@sentry.io
License: MIT
Project-URL: Documentation, https://docs.sentry.io/platforms/python/
Project-URL: Changelog, https://github.com/getsentry/sentry-python/blob/master/CHANGELOG.md
Classifier: Development Status :: 5 - Production/Stable
Classifier: Environment :: Web Environment
Classifier: Intended Audience :: Developers
Classifier: License :: OSI Approved :: BSD License
Classifier: Operating System :: OS Independent
Classifier: Programming Language :: Python
Classifier: Programming Language :: Python :: 2
Classifier: Programming Language :: Python :: 2.7
Classifier: Programming Language :: Python :: 3
Classifier: Programming Language :: Python :: 3.4
Classifier: Programming Language :: Python :: 3.5
Classifier: Programming Language :: Python :: 3.6
Classifier: Programming Language :: Python :: 3.7
Classifier: Programming Language :: Python :: 3.8
Classifier: Programming Language :: Python :: 3.9
Classifier: Programming Language :: Python :: 3.10
Classifier: Programming Language :: Python :: 3.11
Classifier: Programming Language :: Python :: 3.12
Classifier: Topic :: Software Development :: Libraries :: Python Modules
License-File: LICENSE
Requires-Dist: certifi
Requires-Dist: urllib3 >=1.25.7 ; python_version <= "3.4"
Requires-Dist: urllib3 >=1.26.9 ; python_version == "3.5"
Requires-Dist: urllib3 >=1.26.11 ; python_version >= "3.6"
Provides-Extra: aiohttp
Requires-Dist: aiohttp >=3.5 ; extra == 'aiohttp'
Provides-Extra: arq
Requires-Dist: arq >=0.23 ; extra == 'arq'
Provides-Extra: asyncpg
Requires-Dist: asyncpg >=0.23 ; extra == 'asyncpg'
Provides-Extra: beam
Requires-Dist: apache-beam >=2.12 ; extra == 'beam'
Provides-Extra: bottle
Requires-Dist: bottle >=0.12.13 ; extra == 'bottle'
Provides-Extra: celery
Requires-Dist: celery >=3 ; extra == 'celery'
Provides-Extra: chalice
Requires-Dist: chalice >=1.16.0 ; extra == 'chalice'
Provides-Extra: clickhouse-driver
Requires-Dist: clickhouse-driver >=0.2.0 ; extra == 'clickhouse-driver'
Provides-Extra: django
Requires-Dist: django >=1.8 ; extra == 'django'
Provides-Extra: falcon
Requires-Dist: falcon >=1.4 ; extra == 'falcon'
Provides-Extra: fastapi
Requires-Dist: fastapi >=0.79.0 ; extra == 'fastapi'
Provides-Extra: flask
Requires-Dist: flask >=0.11 ; extra == 'flask'
Requires-Dist: blinker >=1.1 ; extra == 'flask'
Requires-Dist: markupsafe ; extra == 'flask'
Provides-Extra: google-cloud-pubsub
Requires-Dist: google-cloud-pubsub ~=2.18.0 ; extra == 'google-cloud-pubsub'
Provides-Extra: grpcio
Requires-Dist: grpcio >=1.21.1 ; extra == 'grpcio'
Provides-Extra: httpx
Requires-Dist: httpx >=0.16.0 ; extra == 'httpx'
Provides-Extra: huey
Requires-Dist: huey >=2 ; extra == 'huey'
Provides-Extra: loguru
Requires-Dist: loguru >=0.5 ; extra == 'loguru'
Provides-Extra: opentelemetry
Requires-Dist: opentelemetry-distro >=0.35b0 ; extra == 'opentelemetry'
Provides-Extra: opentelemetry-experimental
Requires-Dist: opentelemetry-distro ~=0.40b0 ; extra == 'opentelemetry-experimental'
Requires-Dist: opentelemetry-instrumentation-aiohttp-client ~=0.40b0 ; extra == 'opentelemetry-experimental'
Requires-Dist: opentelemetry-instrumentation-django ~=0.40b0 ; extra == 'opentelemetry-experimental'
Requires-Dist: opentelemetry-instrumentation-fastapi ~=0.40b0 ; extra == 'opentelemetry-experimental'
Requires-Dist: opentelemetry-instrumentation-flask ~=0.40b0 ; extra == 'opentelemetry-experimental'
Requires-Dist: opentelemetry-instrumentation-requests ~=0.40b0 ; extra == 'opentelemetry-experimental'
Requires-Dist: opentelemetry-instrumentation-sqlite3 ~=0.40b0 ; extra == 'opentelemetry-experimental'
Requires-Dist: opentelemetry-instrumentation-urllib ~=0.40b0 ; extra == 'opentelemetry-experimental'
Provides-Extra: pure_eval
Requires-Dist: pure-eval ; extra == 'pure_eval'
Requires-Dist: executing ; extra == 'pure_eval'
Requires-Dist: asttokens ; extra == 'pure_eval'
Provides-Extra: pymongo
Requires-Dist: pymongo >=3.1 ; extra == 'pymongo'
Provides-Extra: pyspark
Requires-Dist: pyspark >=2.4.4 ; extra == 'pyspark'
Provides-Extra: quart
Requires-Dist: quart >=0.16.1 ; extra == 'quart'
Requires-Dist: blinker >=1.1 ; extra == 'quart'
Provides-Extra: rq
Requires-Dist: rq >=0.6 ; extra == 'rq'
Provides-Extra: sanic
Requires-Dist: sanic >=0.8 ; extra == 'sanic'
Provides-Extra: sqlalchemy
Requires-Dist: sqlalchemy >=1.2 ; extra == 'sqlalchemy'
Provides-Extra: starlette
Requires-Dist: starlette >=0.19.1 ; extra == 'starlette'
Provides-Extra: starlite
Requires-Dist: starlite >=1.48 ; extra == 'starlite'
Provides-Extra: tornado
Requires-Dist: tornado >=5 ; extra == 'tornado'
